{"seeds": [{"seed": 0, "data": {"tasks": [{"definite": true, "fx": "\\sec\\left(x\\right)^{2} \\tan\\left(x\\right)^{3}", "a": "\\frac{1}{4} \\, \\pi", "b": "\\frac{1}{3} \\, \\pi", "Int": "2", "Fx": "\\frac{1}{4} \\, \\tan\\left(x\\right)^{4}"}, {"indefinite": true, "fx": "\\cos\\left(x\\right)^{2} \\sin\\left(x\\right)^{2}", "Fx": "\\frac{1}{8} \\, x - \\frac{1}{32} \\, \\sin\\left(4 \\, x\\right)"}, {"definite": true, "fx": "\\cos\\left(x\\right)^{3} \\sin\\left(x\\right)^{2}", "a": "0", "b": "\\frac{1}{3} \\, \\pi", "Int": "\\frac{11}{160} \\, \\sqrt{3}", "Fx": "-\\frac{1}{5} \\, \\sin\\left(x\\right)^{5} + \\frac{1}{3} \\, \\sin\\left(x\\right)^{3}"}], "__seed__": "0000"}}, {"seed": 1, "data": {"tasks": [{"definite": true, "fx": "\\cos\\left(x\\right)^{2} \\sin\\left(x\\right)^{5}", "a": "\\frac{1}{4} \\, \\pi", "b": "\\frac{1}{2} \\, \\pi", "Int": "\\frac{71}{1680} \\, \\sqrt{2}", "Fx": "-\\frac{1}{7} \\, \\cos\\left(x\\right)^{7} + \\frac{2}{5} \\, \\cos\\left(x\\right)^{5} - \\frac{1}{3} \\, \\cos\\left(x\\right)^{3}"}, {"definite": true, "fx": "\\sec\\left(x\\right)^{2} \\tan\\left(x\\right)^{3}", "a": "\\frac{1}{6} \\, \\pi", "b": "\\frac{1}{3} \\, \\pi", "Int": "\\frac{20}{9}", "Fx": "\\frac{1}{4} \\, \\tan\\left(x\\right)^{4}"}, {"indefinite": true, "fx": "\\cos\\left(x\\right)^{6} \\sin\\left(x\\right)^{2}", "Fx": "\\frac{1}{48} \\, \\sin\\left(2 \\, x\\right)^{3} + \\frac{5}{128} \\, x - \\frac{1}{1024} \\, \\sin\\left(8 \\, x\\right) - \\frac{1}{128} \\, \\sin\\left(4 \\, x\\right)"}], "__seed__": "0001"}}, {"seed": 2, "data": {"tasks": [{"indefinite": true, "fx": "\\cos\\left(x\\right)^{4} \\sin\\left(x\\right)^{2}", "Fx": "\\frac{1}{48} \\, \\sin\\left(2 \\, x\\right)^{3} + \\frac{1}{16} \\, x - \\frac{1}{64} \\, \\sin\\left(4 \\, x\\right)"}, {"definite": true, "fx": "\\sec\\left(x\\right)^{4} \\tan\\left(x\\right)^{3}", "a": "\\frac{1}{6} \\, \\pi", "b": "\\frac{1}{3} \\, \\pi", "Int": "\\frac{544}{81}", "Fx": "-\\frac{3 \\, \\sin\\left(x\\right)^{2} - 1}{12 \\, {\\left(\\sin\\left(x\\right)^{6} - 3 \\, \\sin\\left(x\\right)^{4} + 3 \\, \\sin\\left(x\\right)^{2} - 1\\right)}}"}, {"definite": true, "fx": "\\cos\\left(x\\right)^{5} \\sin\\left(x\\right)^{2}", "a": "\\frac{1}{6} \\, \\pi", "b": "\\frac{1}{2} \\, \\pi", "Int": "\\frac{617}{13440}", "Fx": "\\frac{1}{7} \\, \\sin\\left(x\\right)^{7} - \\frac{2}{5} \\, \\sin\\left(x\\right)^{5} + \\frac{1}{3} \\, \\sin\\left(x\\right)^{3}"}], "__seed__": "0002"}}, {"seed": 3, "data": {"tasks": [{"definite": true, "fx": "\\cos\\left(x\\right)^{3} \\sin\\left(x\\right)^{5}", "a": "\\frac{1}{6} \\, \\pi", "b": "\\frac{1}{2} \\, \\pi", "Int": "\\frac{81}{2048}", "Fx": "-\\frac{1}{8} \\, \\sin\\left(x\\right)^{8} + \\frac{1}{6} \\, \\sin\\left(x\\right)^{6}"}, {"indefinite": true, "fx": "\\cos\\left(x\\right)^{2} \\sin\\left(x\\right)^{6}", "Fx": "-\\frac{1}{48} \\, \\sin\\left(2 \\, x\\right)^{3} + \\frac{5}{128} \\, x - \\frac{1}{1024} \\, \\sin\\left(8 \\, x\\right) - \\frac{1}{128} \\, \\sin\\left(4 \\, x\\right)"}, {"definite": true, "fx": "\\sec\\left(x\\right)^{2} \\tan\\left(x\\right)", "a": "\\frac{1}{4} \\, \\pi", "b": "\\frac{1}{3} \\, \\pi", "Int": "1", "Fx": "\\frac{1}{2} \\, \\tan\\left(x\\right)^{2}"}], "__seed__": "0003"}}, {"seed": 4, "data": {"tasks": [{"indefinite": true, "fx": "\\cos\\left(x\\right)^{4} \\sin\\left(x\\right)^{2}", "Fx": "\\frac{1}{48} \\, \\sin\\left(2 \\, x\\right)^{3} + \\frac{1}{16} \\, x - \\frac{1}{64} \\, \\sin\\left(4 \\, x\\right)"}, {"definite": true, "fx": "\\cos\\left(x\\right)^{5} \\sin\\left(x\\right)^{3}", "a": "0", "b": "\\frac{1}{3} \\, \\pi", "Int": "\\frac{81}{2048}", "Fx": "\\frac{1}{8} \\, \\sin\\left(x\\right)^{8} - \\frac{1}{3} \\, \\sin\\left(x\\right)^{6} + \\frac{1}{4} \\, \\sin\\left(x\\right)^{4}"}, {"definite": true, "fx": "\\sec\\left(x\\right) \\tan\\left(x\\right)^{3}", "a": "\\frac{1}{6} \\, \\pi", "b": "\\frac{1}{4} \\, \\pi", "Int": "\\frac{10}{27} \\, \\sqrt{3} - \\frac{1}{3} \\, \\sqrt{2}", "Fx": "-\\frac{3 \\, \\cos\\left(x\\right)^{2} - 1}{3 \\, \\cos\\left(x\\right)^{3}}"}], "__seed__": "0004"}}, {"seed": 5, "data": {"tasks": [{"indefinite": true, "fx": "\\cos\\left(x\\right)^{4} \\sin\\left(x\\right)^{2}", "Fx": "\\frac{1}{48} \\, \\sin\\left(2 \\, x\\right)^{3} + \\frac{1}{16} \\, x - \\frac{1}{64} \\, \\sin\\left(4 \\, x\\right)"}, {"definite": true, "fx": "\\cos\\left(x\\right)^{2} \\sin\\left(x\\right)^{3}", "a": "0", "b": "\\frac{1}{3} \\, \\pi", "Int": "\\frac{47}{480}", "Fx": "\\frac{1}{5} \\, \\cos\\left(x\\right)^{5} - \\frac{1}{3} \\, \\cos\\left(x\\right)^{3}"}, {"definite": true, "fx": "\\sec\\left(x\\right)^{4} \\tan\\left(x\\right)^{2}", "a": "\\frac{1}{4} \\, \\pi", "b": "\\frac{1}{3} \\, \\pi", "Int": "\\frac{14}{5} \\, \\sqrt{3} - \\frac{8}{15}", "Fx": "\\frac{1}{5} \\, \\tan\\left(x\\right)^{5} + \\frac{1}{3} \\, \\tan\\left(x\\right)^{3}"}], "__seed__": "0005"}}, {"seed": 6, "data": {"tasks": [{"definite": true, "fx": "\\cos\\left(x\\right)^{3} \\sin\\left(x\\right)^{5}", "a": "0", "b": "\\frac{1}{6} \\, \\pi", "Int": "\\frac{13}{6144}", "Fx": "-\\frac{1}{8} \\, \\sin\\left(x\\right)^{8} + \\frac{1}{6} \\, \\sin\\left(x\\right)^{6}"}, {"indefinite": true, "fx": "\\cos\\left(x\\right)^{2} \\sin\\left(x\\right)^{2}", "Fx": "\\frac{1}{8} \\, x - \\frac{1}{32} \\, \\sin\\left(4 \\, x\\right)"}, {"definite": true, "fx": "\\sec\\left(x\\right)^{2} \\tan\\left(x\\right)^{3}", "a": "\\frac{1}{6} \\, \\pi", "b": "\\frac{1}{3} \\, \\pi", "Int": "\\frac{20}{9}", "Fx": "\\frac{1}{4} \\, \\tan\\left(x\\right)^{4}"}], "__seed__": "0006"}}, {"seed": 7, "data": {"tasks": [{"indefinite": true, "fx": "\\cos\\left(x\\right)^{2} \\sin\\left(x\\right)^{2}", "Fx": "\\frac{1}{8} \\, x - \\frac{1}{32} \\, \\sin\\left(4 \\, x\\right)"}, {"definite": true, "fx": "\\sec\\left(x\\right)^{2} \\tan\\left(x\\right)^{5}", "a": "\\frac{1}{6} \\, \\pi", "b": "\\frac{1}{4} \\, \\pi", "Int": "\\frac{13}{81}", "Fx": "\\frac{1}{6} \\, \\tan\\left(x\\right)^{6}"}, {"definite": true, "fx": "\\cos\\left(x\\right)^{5} \\sin\\left(x\\right)^{3}", "a": "\\frac{1}{6} \\, \\pi", "b": "\\frac{1}{3} \\, \\pi", "Int": "\\frac{11}{384}", "Fx": "\\frac{1}{8} \\, \\sin\\left(x\\right)^{8} - \\frac{1}{3} \\, \\sin\\left(x\\right)^{6} + \\frac{1}{4} \\, \\sin\\left(x\\right)^{4}"}], "__seed__": "0007"}}, {"seed": 8, "data": {"tasks": [{"definite": true, "fx": "\\sec\\left(x\\right)^{2} \\tan\\left(x\\right)^{3}", "a": "\\frac{1}{6} \\, \\pi", "b": "\\frac{1}{4} \\, \\pi", "Int": "\\frac{2}{9}", "Fx": "\\frac{1}{4} \\, \\tan\\left(x\\right)^{4}"}, {"definite": true, "fx": "\\cos\\left(x\\right)^{2} \\sin\\left(x\\right)^{5}", "a": "0", "b": "\\frac{1}{6} \\, \\pi", "Int": "-\\frac{191}{4480} \\, \\sqrt{3} + \\frac{8}{105}", "Fx": "-\\frac{1}{7} \\, \\cos\\left(x\\right)^{7} + \\frac{2}{5} \\, \\cos\\left(x\\right)^{5} - \\frac{1}{3} \\, \\cos\\left(x\\right)^{3}"}, {"indefinite": true, "fx": "\\cos\\left(x\\right)^{2} \\sin\\left(x\\right)^{6}", "Fx": "-\\frac{1}{48} \\, \\sin\\left(2 \\, x\\right)^{3} + \\frac{5}{128} \\, x - \\frac{1}{1024} \\, \\sin\\left(8 \\, x\\right) - \\frac{1}{128} \\, \\sin\\left(4 \\, x\\right)"}], "__seed__": "0008"}}, {"seed": 9, "data": {"tasks": [{"indefinite": true, "fx": "\\cos\\left(x\\right)^{2} \\sin\\left(x\\right)^{6}", "Fx": "-\\frac{1}{48} \\, \\sin\\left(2 \\, x\\right)^{3} + \\frac{5}{128} \\, x - \\frac{1}{1024} \\, \\sin\\left(8 \\, x\\right) - \\frac{1}{128} \\, \\sin\\left(4 \\, x\\right)"}, {"definite": true, "fx": "\\cos\\left(x\\right)^{3} \\sin\\left(x\\right)^{5}", "a": "0", "b": "\\frac{1}{4} \\, \\pi", "Int": "\\frac{5}{384}", "Fx": "-\\frac{1}{8} \\, \\sin\\left(x\\right)^{8} + \\frac{1}{6} \\, \\sin\\left(x\\right)^{6}"}, {"definite": true, "fx": "\\sec\\left(x\\right)^{2} \\tan\\left(x\\right)^{2}", "a": "\\frac{1}{6} \\, \\pi", "b": "\\frac{1}{4} \\, \\pi", "Int": "-\\frac{1}{27} \\, \\sqrt{3} + \\frac{1}{3}", "Fx": "\\frac{1}{3} \\, \\tan\\left(x\\right)^{3}"}], "__seed__": "0009"}}, {"seed": 10, "data": {"tasks": [{"definite": true, "fx": "\\cos\\left(x\\right)^{3} \\sin\\left(x\\right)^{5}", "a": "\\frac{1}{6} \\, \\pi", "b": "\\frac{1}{4} \\, \\pi", "Int": "\\frac{67}{6144}", "Fx": "-\\frac{1}{8} \\, \\sin\\left(x\\right)^{8} + \\frac{1}{6} \\, \\sin\\left(x\\right)^{6}"}, {"definite": true, "fx": "\\sec\\left(x\\right)^{4} \\tan\\left(x\\right)", "a": "\\frac{1}{6} \\, \\pi", "b": "\\frac{1}{4} \\, \\pi", "Int": "\\frac{5}{9}", "Fx": "\\frac{1}{4 \\, {\\left(\\sin\\left(x\\right)^{2} - 1\\right)}^{2}}"}, {"indefinite": true, "fx": "\\cos\\left(x\\right)^{2} \\sin\\left(x\\right)^{2}", "Fx": "\\frac{1}{8} \\, x - \\frac{1}{32} \\, \\sin\\left(4 \\, x\\right)"}], "__seed__": "0010"}}, {"seed": 11, "data": {"tasks": [{"indefinite": true, "fx": "\\cos\\left(x\\right)^{4} \\sin\\left(x\\right)^{2}", "Fx": "\\frac{1}{48} \\, \\sin\\left(2 \\, x\\right)^{3} + \\frac{1}{16} \\, x - \\frac{1}{64} \\, \\sin\\left(4 \\, x\\right)"}, {"definite": true, "fx": "\\cos\\left(x\\right)^{2} \\sin\\left(x\\right)^{5}", "a": "\\frac{1}{4} \\, \\pi", "b": "\\frac{1}{3} \\, \\pi", "Int": "\\frac{71}{1680} \\, \\sqrt{2} - \\frac{407}{13440}", "Fx": "-\\frac{1}{7} \\, \\cos\\left(x\\right)^{7} + \\frac{2}{5} \\, \\cos\\left(x\\right)^{5} - \\frac{1}{3} \\, \\cos\\left(x\\right)^{3}"}, {"definite": true, "fx": "\\sec\\left(x\\right)^{4} \\tan\\left(x\\right)", "a": "\\frac{1}{4} \\, \\pi", "b": "\\frac{1}{3} \\, \\pi", "Int": "3", "Fx": "\\frac{1}{4 \\, {\\left(\\sin\\left(x\\right)^{2} - 1\\right)}^{2}}"}], "__seed__": "0011"}}, {"seed": 12, "data": {"tasks": [{"indefinite": true, "fx": "\\cos\\left(x\\right)^{2} \\sin\\left(x\\right)^{6}", "Fx": "-\\frac{1}{48} \\, \\sin\\left(2 \\, x\\right)^{3} + \\frac{5}{128} \\, x - \\frac{1}{1024} \\, \\sin\\left(8 \\, x\\right) - \\frac{1}{128} \\, \\sin\\left(4 \\, x\\right)"}, {"definite": true, "fx": "\\cos\\left(x\\right)^{3} \\sin\\left(x\\right)^{5}", "a": "\\frac{1}{3} \\, \\pi", "b": "\\frac{1}{2} \\, \\pi", "Int": "\\frac{67}{6144}", "Fx": "-\\frac{1}{8} \\, \\sin\\left(x\\right)^{8} + \\frac{1}{6} \\, \\sin\\left(x\\right)^{6}"}, {"definite": true, "fx": "\\sec\\left(x\\right)^{2} \\tan\\left(x\\right)^{2}", "a": "\\frac{1}{6} \\, \\pi", "b": "\\frac{1}{4} \\, \\pi", "Int": "-\\frac{1}{27} \\, \\sqrt{3} + \\frac{1}{3}", "Fx": "\\frac{1}{3} \\, \\tan\\left(x\\right)^{3}"}], "__seed__": "0012"}}, {"seed": 13, "data": {"tasks": [{"indefinite": true, "fx": "\\cos\\left(x\\right)^{4} \\sin\\left(x\\right)^{2}", "Fx": "\\frac{1}{48} \\, \\sin\\left(2 \\, x\\right)^{3} + \\frac{1}{16} \\, x - \\frac{1}{64} \\, \\sin\\left(4 \\, x\\right)"}, {"definite": true, "fx": "\\sec\\left(x\\right)^{4} \\tan\\left(x\\right)^{2}", "a": "\\frac{1}{4} \\, \\pi", "b": "\\frac{1}{3} \\, \\pi", "Int": "\\frac{14}{5} \\, \\sqrt{3} - \\frac{8}{15}", "Fx": "\\frac{1}{5} \\, \\tan\\left(x\\right)^{5} + \\frac{1}{3} \\, \\tan\\left(x\\right)^{3}"}, {"definite": true, "fx": "\\cos\\left(x\\right)^{3} \\sin\\left(x\\right)^{2}", "a": "\\frac{1}{4} \\, \\pi", "b": "\\frac{1}{3} \\, \\pi", "Int": "\\frac{11}{160} \\, \\sqrt{3} - \\frac{7}{120} \\, \\sqrt{2}", "Fx": "-\\frac{1}{5} \\, \\sin\\left(x\\right)^{5} + \\frac{1}{3} \\, \\sin\\left(x\\right)^{3}"}], "__seed__": "0013"}}, {"seed": 14, "data": {"tasks": [{"definite": true, "fx": "\\cos\\left(x\\right)^{2} \\sin\\left(x\\right)^{3}", "a": "\\frac{1}{4} \\, \\pi", "b": "\\frac{1}{3} \\, \\pi", "Int": "\\frac{7}{120} \\, \\sqrt{2} - \\frac{17}{480}", "Fx": "\\frac{1}{5} \\, \\cos\\left(x\\right)^{5} - \\frac{1}{3} \\, \\cos\\left(x\\right)^{3}"}, {"definite": true, "fx": "\\sec\\left(x\\right)^{2} \\tan\\left(x\\right)^{2}", "a": "\\frac{1}{6} \\, \\pi", "b": "\\frac{1}{3} \\, \\pi", "Int": "\\frac{26}{27} \\, \\sqrt{3}", "Fx": "\\frac{1}{3} \\, \\tan\\left(x\\right)^{3}"}, {"indefinite": true, "fx": "\\cos\\left(x\\right)^{2} \\sin\\left(x\\right)^{6}", "Fx": "-\\frac{1}{48} \\, \\sin\\left(2 \\, x\\right)^{3} + \\frac{5}{128} \\, x - \\frac{1}{1024} \\, \\sin\\left(8 \\, x\\right) - \\frac{1}{128} \\, \\sin\\left(4 \\, x\\right)"}], "__seed__": "0014"}}, {"seed": 15, "data": {"tasks": [{"definite": true, "fx": "\\cos\\left(x\\right)^{3} \\sin\\left(x\\right)^{3}", "a": "0", "b": "\\frac{1}{3} \\, \\pi", "Int": "\\frac{9}{128}", "Fx": "-\\frac{1}{6} \\, \\sin\\left(x\\right)^{6} + \\frac{1}{4} \\, \\sin\\left(x\\right)^{4}"}, {"definite": true, "fx": "\\sec\\left(x\\right)^{2} \\tan\\left(x\\right)", "a": "\\frac{1}{6} \\, \\pi", "b": "\\frac{1}{4} \\, \\pi", "Int": "\\frac{1}{3}", "Fx": "\\frac{1}{2} \\, \\tan\\left(x\\right)^{2}"}, {"indefinite": true, "fx": "\\cos\\left(x\\right)^{2} \\sin\\left(x\\right)^{2}", "Fx": "\\frac{1}{8} \\, x - \\frac{1}{32} \\, \\sin\\left(4 \\, x\\right)"}], "__seed__": "0015"}}, {"seed": 16, "data": {"tasks": [{"definite": true, "fx": "\\cos\\left(x\\right)^{5} \\sin\\left(x\\right)^{2}", "a": "\\frac{1}{4} \\, \\pi", "b": "\\frac{1}{3} \\, \\pi", "Int": "\\frac{191}{4480} \\, \\sqrt{3} - \\frac{71}{1680} \\, \\sqrt{2}", "Fx": "\\frac{1}{7} \\, \\sin\\left(x\\right)^{7} - \\frac{2}{5} \\, \\sin\\left(x\\right)^{5} + \\frac{1}{3} \\, \\sin\\left(x\\right)^{3}"}, {"definite": true, "fx": "\\sec\\left(x\\right)^{2} \\tan\\left(x\\right)^{3}", "a": "\\frac{1}{4} \\, \\pi", "b": "\\frac{1}{3} \\, \\pi", "Int": "2", "Fx": "\\frac{1}{4} \\, \\tan\\left(x\\right)^{4}"}, {"indefinite": true, "fx": "\\cos\\left(x\\right)^{6} \\sin\\left(x\\right)^{2}", "Fx": "\\frac{1}{48} \\, \\sin\\left(2 \\, x\\right)^{3} + \\frac{5}{128} \\, x - \\frac{1}{1024} \\, \\sin\\left(8 \\, x\\right) - \\frac{1}{128} \\, \\sin\\left(4 \\, x\\right)"}], "__seed__": "0016"}}, {"seed": 17, "data": {"tasks": [{"definite": true, "fx": "\\cos\\left(x\\right)^{3} \\sin\\left(x\\right)^{5}", "a": "0", "b": "\\frac{1}{3} \\, \\pi", "Int": "\\frac{63}{2048}", "Fx": "-\\frac{1}{8} \\, \\sin\\left(x\\right)^{8} + \\frac{1}{6} \\, \\sin\\left(x\\right)^{6}"}, {"definite": true, "fx": "\\sec\\left(x\\right)^{2} \\tan\\left(x\\right)^{3}", "a": "\\frac{1}{4} \\, \\pi", "b": "\\frac{1}{3} \\, \\pi", "Int": "2", "Fx": "\\frac{1}{4} \\, \\tan\\left(x\\right)^{4}"}, {"indefinite": true, "fx": "\\cos\\left(x\\right)^{6} \\sin\\left(x\\right)^{2}", "Fx": "\\frac{1}{48} \\, \\sin\\left(2 \\, x\\right)^{3} + \\frac{5}{128} \\, x - \\frac{1}{1024} \\, \\sin\\left(8 \\, x\\right) - \\frac{1}{128} \\, \\sin\\left(4 \\, x\\right)"}], "__seed__": "0017"}}, {"seed": 18, "data": {"tasks": [{"definite": true, "fx": "\\sec\\left(x\\right)^{2} \\tan\\left(x\\right)^{5}", "a": "\\frac{1}{6} \\, \\pi", "b": "\\frac{1}{4} \\, \\pi", "Int": "\\frac{13}{81}", "Fx": "\\frac{1}{6} \\, \\tan\\left(x\\right)^{6}"}, {"definite": true, "fx": "\\cos\\left(x\\right)^{5} \\sin\\left(x\\right)^{3}", "a": "0", "b": "\\frac{1}{6} \\, \\pi", "Int": "\\frac{67}{6144}", "Fx": "\\frac{1}{8} \\, \\sin\\left(x\\right)^{8} - \\frac{1}{3} \\, \\sin\\left(x\\right)^{6} + \\frac{1}{4} \\, \\sin\\left(x\\right)^{4}"}, {"indefinite": true, "fx": "\\cos\\left(x\\right)^{6} \\sin\\left(x\\right)^{2}", "Fx": "\\frac{1}{48} \\, \\sin\\left(2 \\, x\\right)^{3} + \\frac{5}{128} \\, x - \\frac{1}{1024} \\, \\sin\\left(8 \\, x\\right) - \\frac{1}{128} \\, \\sin\\left(4 \\, x\\right)"}], "__seed__": "0018"}}, {"seed": 19, "data": {"tasks": [{"indefinite": true, "fx": "\\cos\\left(x\\right)^{2} \\sin\\left(x\\right)^{2}", "Fx": "\\frac{1}{8} \\, x - \\frac{1}{32} \\, \\sin\\left(4 \\, x\\right)"}, {"definite": true, "fx": "\\sec\\left(x\\right)^{2} \\tan\\left(x\\right)^{3}", "a": "\\frac{1}{6} \\, \\pi", "b": "\\frac{1}{4} \\, \\pi", "Int": "\\frac{2}{9}", "Fx": "\\frac{1}{4} \\, \\tan\\left(x\\right)^{4}"}, {"definite": true, "fx": "\\cos\\left(x\\right)^{3} \\sin\\left(x\\right)^{5}", "a": "0", "b": "\\frac{1}{6} \\, \\pi", "Int": "\\frac{13}{6144}", "Fx": "-\\frac{1}{8} \\, \\sin\\left(x\\right)^{8} + \\frac{1}{6} \\, \\sin\\left(x\\right)^{6}"}], "__seed__": "0019"}}], "generated_on": "2026-05-15T22:38:17.517070+00:00"}